AUTHORS.rst
CHANGELOG.rst
CONTRIBUTING.rst
LICENSE
README.rst
setup.py
commando/__init__.py
commando/_compat.py
commando/application.py
commando/conf.py
commando/util.py
commando.egg-info/PKG-INFO
commando.egg-info/SOURCES.txt
commando.egg-info/dependency_links.txt
commando.egg-info/top_level.txt
commando/tests/__init__.py
commando/tests/dev-req.txt
commando/tests/test_commando.py
commando/tests/test_conf.py
commando/tests/test_loader.py