Metadata-Version: 1.1
Name: commando
Version: 1.0.0
Summary: A declarative interface to argparse and extras.
Home-page: http://github.com/hyde/commando
Author: Lakshmi Vyas
Author-email: lakshmi.vyas@gmail.com
License: MIT
Keywords: argparse commandline utility
Platform: UNKNOWN
Classifier: Development Status :: 3 - Alpha
Classifier: Environment :: Console
Classifier: Intended Audience :: Developers
Classifier: License :: OSI Approved :: MIT License
Classifier: Operating System :: OS Independent
Classifier: Programming Language :: Python
Classifier: Topic :: Software Development :: User Interfaces
Classifier: Topic :: Software Development :: Libraries :: Python Modules
Requires: python (>= 2.7)
Provides: commando
